vtb_logger/__init__.py
vtb_logger/aux_logger.py
vtb_logger/aux/__init__.py
vtb_logger/aux/aux_dir_and_files.py
vtb_logger/aux/aux_quer.py
vtb_logger/aux/aux_shared.py
vtb_logger/aux/setup.py
vtb_logger-2.6.0.dist-info/METADATA
vtb_logger-2.6.0.dist-info/WHEEL
vtb_logger-2.6.0.dist-info/top_level.txt
vtb_logger-2.6.0.dist-info/RECORD
