Metadata-Version: 2.2
Name: vtb-logger
Version: 2.6.0
Summary: A simple Python package
Home-page: https://github.com/vtb-wanderers63/py-logging-module
Author: VTB Wanderer DG
Author-email: vtb.wanderers63@gmail.com
Classifier: Programming Language :: Python :: 3
Classifier: License :: OSI Approved :: MIT License
Classifier: Operating System :: OS Independent
Requires-Python: >=3.7
Requires-Dist: confluent-kafka
Requires-Dist: python-dotenv
Dynamic: author
Dynamic: author-email
Dynamic: classifier
Dynamic: description
Dynamic: description-content-type
Dynamic: home-page
Dynamic: requires-dist
Dynamic: requires-python
Dynamic: summary
